{
  "performanceSummary":
  {
    "name":"Kernel Summary"
    , "columns":
    ["Kernel Name", "Kernel Type", "Autorun", "Workgroup Size", "# Compute Units", "HyperFlex Control Optimizations"]
    , "children":
    [
      {
        "name":"DotProduct"
        , "data":
        [
          "NDRange"
          , "No"
          , "n/a"
          , 1
          , "On"
        ]
        , "details":
        [
          {
            "type":"text"
            , "text":"Kernel type: NDRange"
          }
          , {
            "type":"text"
            , "text":"The kernel does not use any work-group information (such as get_local_id() or get_group_id()).Local work-group size will be automatically modified to match global work-group size on launch.This is a hardware optimization."
          }
        ]
        , "debug":
        [
          [
            {
              "filename":"/export/data/users/angelicadg/exm_grendel_GX/DotProduct/DotProduct.cl"
              , "line":23
            }
          ]
        ]
      }
    ]
  }
  , "estimatedResources":
  {
    "name":"Estimated Resource Usage"
    , "columns":
    ["Kernel Name", "ALUTs ", "FFs  ", "RAMs ", "DSPs ", "MLABs"]
    , "children":
    [
      {
        "name":"DotProduct"
        , "data":
        [3301, 8928, 51, 4, 15]
        , "debug":
        [
          [
            {
              "filename":"/export/data/users/angelicadg/exm_grendel_GX/DotProduct/DotProduct.cl"
              , "line":23
            }
          ]
        ]
      }
      , {
        "name":"Global Interconnect"
        , "classes":
        ["summary-highlight", "nohover"]
        , "data":
        [4121, 5284, 0, 0, 0]
      }
      , {
        "name":"Board Interface"
        , "classes":
        ["summary-highlight", "nohover"]
        , "data":
        [13132, 20030, 112, 0, 0]
      }
      , {
        "name":"Total"
        , "classes":
        ["summary-highlight", "nohover"]
        , "data":
        [20556, 34313, 165, 4, 15]
        , "data_percent":
        [1.10927, 0.924268, 1.42131, 0.0694444, 1.9507]
      }
      , {
        "name":"Available"
        , "classes":
        ["summary-highlight", "nohover"]
        , "data":
        [1853108, 3712450, 11609, 5760, 0]
      }
    ]
  }
  , "compileWarnings":
  {
    "name":"Compile Warnings"
    , "children":
    [
    ]
  }
}
