{
  "254346648":
  {
    "nodes":
    [
      {
        "name":"test_multiplereads.B0"
        , "id":254512480
        , "start":"0"
        , "end":"658"
        , "details":
        [
          {
            "type":"table"
          }
        ]
        , "type":"bb"
        , "children":
        [
          {
            "name":"Cluster 0"
            , "id":257087648
            , "start":"0"
            , "end":"34"
            , "details":
            [
              {
                "type":"table"
                , "Cluster Name":"i_sfc_s_c0_in_entry_test_multiplereadss_c0_enter_test_multiplereads1"
                , "Cluster Type":"Stall-Free"
                , "Cluster Start Cycle":"0"
                , "Cluster Latency":"34"
              }
            ]
            , "type":"cluster"
            , "children":
            [
              {
                "name":"<<"
                , "id":258824816
                , "start":"0"
                , "end":"0"
                , "details":
                [
                  {
                    "type":"table"
                    , "Instruction":"64-bit Left Shift"
                    , "Constant Operand":"33 (0x21)"
                    , "Start Cycle":"0"
                    , "Latency":"0"
                  }
                ]
                , "type":"inst"
              }
              , {
                "name":">>"
                , "id":258970096
                , "start":"0"
                , "end":"0"
                , "details":
                [
                  {
                    "type":"table"
                    , "Instruction":"64-bit Arithmetic Right Shift"
                    , "Constant Operand":"32 (0x20)"
                    , "Start Cycle":"0"
                    , "Latency":"0"
                  }
                ]
                , "debug":
                [
                  [
                    {
                      "filename":"test_bw10.cl"
                      , "line":39
                    }
                  ]
                ]
                , "type":"inst"
              }
              , {
                "name":"y"
                , "id":257330784
                , "start":"0"
                , "end":"3"
                , "details":
                [
                  {
                    "type":"table"
                    , "Instruction":"Input Synchronization for 'y'"
                    , "Start Cycle":"0"
                    , "Latency":"3"
                  }
                ]
                , "type":"inst"
              }
              , {
                "name":"Ptr. Comp."
                , "id":258759840
                , "start":"0"
                , "end":"3"
                , "details":
                [
                  {
                    "type":"table"
                    , "Instruction":"Pointer Computation"
                    , "Start Cycle":"0"
                    , "Latency":"3"
                  }
                ]
                , "debug":
                [
                  [
                    {
                      "filename":"test_bw10.cl"
                      , "line":39
                    }
                  ]
                ]
                , "type":"inst"
              }
              , {
                "name":"y2"
                , "id":258102144
                , "start":"0"
                , "end":"3"
                , "details":
                [
                  {
                    "type":"table"
                    , "Instruction":"Input Synchronization for 'y2'"
                    , "Start Cycle":"0"
                    , "Latency":"3"
                  }
                ]
                , "type":"inst"
              }
              , {
                "name":"Ptr. Comp."
                , "id":266519056
                , "start":"0"
                , "end":"3"
                , "details":
                [
                  {
                    "type":"table"
                    , "Instruction":"Pointer Computation"
                    , "Start Cycle":"0"
                    , "Latency":"3"
                  }
                ]
                , "debug":
                [
                  [
                    {
                      "filename":"test_bw10.cl"
                      , "line":39
                    }
                  ]
                ]
                , "type":"inst"
              }
              , {
                "name":"x"
                , "id":258783360
                , "start":"0"
                , "end":"3"
                , "details":
                [
                  {
                    "type":"table"
                    , "Instruction":"Input Synchronization for 'x'"
                    , "Start Cycle":"0"
                    , "Latency":"3"
                  }
                ]
                , "type":"inst"
              }
              , {
                "name":"Ptr. Comp."
                , "id":258962000
                , "start":"0"
                , "end":"3"
                , "details":
                [
                  {
                    "type":"table"
                    , "Instruction":"Pointer Computation"
                    , "Start Cycle":"0"
                    , "Latency":"3"
                  }
                ]
                , "debug":
                [
                  [
                    {
                      "filename":"test_bw10.cl"
                      , "line":39
                    }
                  ]
                ]
                , "type":"inst"
              }
              , {
                "name":"y1"
                , "id":258801856
                , "start":"0"
                , "end":"3"
                , "details":
                [
                  {
                    "type":"table"
                    , "Instruction":"Input Synchronization for 'y1'"
                    , "Start Cycle":"0"
                    , "Latency":"3"
                  }
                ]
                , "type":"inst"
              }
              , {
                "name":"Ptr. Comp."
                , "id":257785920
                , "start":"0"
                , "end":"3"
                , "details":
                [
                  {
                    "type":"table"
                    , "Instruction":"Pointer Computation"
                    , "Start Cycle":"0"
                    , "Latency":"3"
                  }
                ]
                , "debug":
                [
                  [
                    {
                      "filename":"test_bw10.cl"
                      , "line":39
                    }
                  ]
                ]
                , "type":"inst"
              }
              , {
                "name":"z"
                , "id":261600032
                , "start":"0"
                , "end":"3"
                , "details":
                [
                  {
                    "type":"table"
                    , "Instruction":"Input Synchronization for 'z'"
                    , "Start Cycle":"0"
                    , "Latency":"3"
                  }
                ]
                , "type":"inst"
              }
              , {
                "name":"Ptr. Comp."
                , "id":261550176
                , "start":"0"
                , "end":"3"
                , "details":
                [
                  {
                    "type":"table"
                    , "Instruction":"Pointer Computation"
                    , "Start Cycle":"0"
                    , "Latency":"3"
                  }
                ]
                , "debug":
                [
                  [
                    {
                      "filename":"test_bw10.cl"
                      , "line":39
                    }
                  ]
                ]
                , "type":"inst"
              }
              , {
                "name":"Exit"
                , "id":261580496
                , "start":"3"
                , "end":"34"
                , "details":
                [
                  {
                    "type":"table"
                    , "Exit Start Cycle":"3"
                    , "Exit Latency":"31"
                    , "Exit FIFO Depth":"64"
                    , "Exit FIFO Width":"384"
                    , "Details":"Exit FIFO depth is sized to accommodate all data that may be in-flight in the stall-free cluster; this depth will be equal to or greater than the latency of the cluster.  The width of the FIFO depends on the amount of data that needs to pass from the stall-free logic cluster to the stall-able logic below it."
                  }
                ]
                , "type":"inst"
              }
            ]
          }
          , {
            "name":"LD"
            , "id":266510752
            , "start":"34"
            , "end":"546"
            , "details":
            [
              {
                "type":"table"
                , "Instruction":"Load"
                , "Width":"64 bits"
                , "LSU Style":"Burst-coalesced"
                , "Stall-free":"No"
                , "Global Memory":"Yes"
                , "Start Cycle":"34"
                , "Latency":"512"
              }
            ]
            , "debug":
            [
              [
                {
                  "filename":"test_bw10.cl"
                  , "line":39
                }
              ]
            ]
            , "type":"inst"
          }
          , {
            "name":"LD"
            , "id":261636384
            , "start":"34"
            , "end":"546"
            , "details":
            [
              {
                "type":"table"
                , "Instruction":"Load"
                , "Width":"64 bits"
                , "LSU Style":"Burst-coalesced"
                , "Stall-free":"No"
                , "Global Memory":"Yes"
                , "Start Cycle":"34"
                , "Latency":"512"
              }
            ]
            , "debug":
            [
              [
                {
                  "filename":"test_bw10.cl"
                  , "line":39
                }
              ]
            ]
            , "type":"inst"
          }
          , {
            "name":"LD"
            , "id":261621696
            , "start":"34"
            , "end":"546"
            , "details":
            [
              {
                "type":"table"
                , "Instruction":"Load"
                , "Width":"64 bits"
                , "LSU Style":"Burst-coalesced"
                , "Stall-free":"No"
                , "Global Memory":"Yes"
                , "Start Cycle":"34"
                , "Latency":"512"
              }
            ]
            , "debug":
            [
              [
                {
                  "filename":"test_bw10.cl"
                  , "line":39
                }
              ]
            ]
            , "type":"inst"
          }
          , {
            "name":"LD"
            , "id":261548832
            , "start":"34"
            , "end":"546"
            , "details":
            [
              {
                "type":"table"
                , "Instruction":"Load"
                , "Width":"64 bits"
                , "LSU Style":"Burst-coalesced"
                , "Stall-free":"No"
                , "Global Memory":"Yes"
                , "Start Cycle":"34"
                , "Latency":"512"
              }
            ]
            , "debug":
            [
              [
                {
                  "filename":"test_bw10.cl"
                  , "line":39
                }
              ]
            ]
            , "type":"inst"
          }
          , {
            "name":"Cluster 2"
            , "id":257553616
            , "start":"546"
            , "end":"594"
            , "details":
            [
              {
                "type":"table"
                , "Cluster Name":"i_sfc_s_c2_in_entry_test_multiplereadss_c2_enter_test_multiplereads11"
                , "Cluster Type":"Stall-Free"
                , "Cluster Start Cycle":"546"
                , "Cluster Latency":"48"
              }
            ]
            , "type":"cluster"
            , "children":
            [
              {
                "name":"Hard FP +"
                , "id":261763216
                , "start":"546"
                , "end":"551"
                , "details":
                [
                  {
                    "type":"table"
                    , "Instruction":"Hardened Floating-point Add"
                    , "Start Cycle":"546"
                    , "Latency":"5"
                  }
                ]
                , "debug":
                [
                  [
                    {
                      "filename":"test_bw10.cl"
                      , "line":39
                    }
                  ]
                ]
                , "type":"inst"
              }
              , {
                "name":"Hard FP +"
                , "id":261764560
                , "start":"552"
                , "end":"557"
                , "details":
                [
                  {
                    "type":"table"
                    , "Instruction":"Hardened Floating-point Add"
                    , "Start Cycle":"552"
                    , "Latency":"5"
                  }
                ]
                , "debug":
                [
                  [
                    {
                      "filename":"test_bw10.cl"
                      , "line":39
                    }
                  ]
                ]
                , "type":"inst"
              }
              , {
                "name":"Hard FP +"
                , "id":260290016
                , "start":"558"
                , "end":"563"
                , "details":
                [
                  {
                    "type":"table"
                    , "Instruction":"Hardened Floating-point Add"
                    , "Start Cycle":"558"
                    , "Latency":"5"
                  }
                ]
                , "debug":
                [
                  [
                    {
                      "filename":"test_bw10.cl"
                      , "line":39
                    }
                  ]
                ]
                , "type":"inst"
              }
              , {
                "name":"Hard FP +"
                , "id":261762880
                , "start":"546"
                , "end":"551"
                , "details":
                [
                  {
                    "type":"table"
                    , "Instruction":"Hardened Floating-point Add"
                    , "Start Cycle":"546"
                    , "Latency":"5"
                  }
                ]
                , "debug":
                [
                  [
                    {
                      "filename":"test_bw10.cl"
                      , "line":39
                    }
                  ]
                ]
                , "type":"inst"
              }
              , {
                "name":"Hard FP +"
                , "id":261764224
                , "start":"552"
                , "end":"557"
                , "details":
                [
                  {
                    "type":"table"
                    , "Instruction":"Hardened Floating-point Add"
                    , "Start Cycle":"552"
                    , "Latency":"5"
                  }
                ]
                , "debug":
                [
                  [
                    {
                      "filename":"test_bw10.cl"
                      , "line":39
                    }
                  ]
                ]
                , "type":"inst"
              }
              , {
                "name":"Hard FP +"
                , "id":260289680
                , "start":"558"
                , "end":"563"
                , "details":
                [
                  {
                    "type":"table"
                    , "Instruction":"Hardened Floating-point Add"
                    , "Start Cycle":"558"
                    , "Latency":"5"
                  }
                ]
                , "debug":
                [
                  [
                    {
                      "filename":"test_bw10.cl"
                      , "line":39
                    }
                  ]
                ]
                , "type":"inst"
              }
              , {
                "name":"Exit"
                , "id":257345936
                , "start":"563"
                , "end":"594"
                , "details":
                [
                  {
                    "type":"table"
                    , "Exit Start Cycle":"563"
                    , "Exit Latency":"31"
                    , "Exit FIFO Depth":"64"
                    , "Exit FIFO Width":"72"
                    , "Details":"Exit FIFO depth is sized to accommodate all data that may be in-flight in the stall-free cluster; this depth will be equal to or greater than the latency of the cluster.  The width of the FIFO depends on the amount of data that needs to pass from the stall-free logic cluster to the stall-able logic below it."
                  }
                ]
                , "type":"inst"
              }
            ]
          }
          , {
            "name":"Cluster 1"
            , "id":257517680
            , "start":"34"
            , "end":"65"
            , "details":
            [
              {
                "type":"table"
                , "Cluster Name":"i_sfc_s_c1_in_entry_test_multiplereadss_c1_enter_test_multiplereads8"
                , "Cluster Type":"Stall-Free"
                , "Cluster Start Cycle":"34"
                , "Cluster Latency":"31"
              }
            ]
            , "type":"cluster"
            , "children":
            [
              {
                "name":"Exit"
                , "id":259602256
                , "start":"34"
                , "end":"65"
                , "details":
                [
                  {
                    "type":"table"
                    , "Exit Start Cycle":"34"
                    , "Exit Latency":"31"
                    , "Exit FIFO Depth":"32"
                    , "Exit FIFO Width":"128"
                    , "Details":"Exit FIFO depth is sized to accommodate all data that may be in-flight in the stall-free cluster; this depth will be equal to or greater than the latency of the cluster.  The width of the FIFO depends on the amount of data that needs to pass from the stall-free logic cluster to the stall-able logic below it."
                  }
                ]
                , "type":"inst"
              }
            ]
          }
          , {
            "name":"ST"
            , "id":258873808
            , "start":"594"
            , "end":"658"
            , "details":
            [
              {
                "type":"table"
                , "Instruction":"Store"
                , "Width":"64 bits"
                , "LSU Style":"Burst-coalesced"
                , "Stall-free":"No"
                , "Global Memory":"Yes"
                , "Start Cycle":"594"
                , "Latency":"64"
              }
            ]
            , "debug":
            [
              [
                {
                  "filename":"test_bw10.cl"
                  , "line":39
                }
              ]
            ]
            , "type":"inst"
          }
        ]
      }
    ]
    , "links":
    [
    ]
  }
}
