{
  "performanceSummary":
  {
    "name":"Kernel Summary"
    , "columns":
    ["Kernel Name", "Kernel Type", "Autorun", "Workgroup Size", "# Compute Units", "Hyper-Optimized Handshaking"]
    , "children":
    [
      {
        "name":"streaming_iamax"
        , "data":
        [
          "Single work-item"
          , "No"
          , [1, 1, 1]
          , 1
          , "On"
        ]
        , "details":
        [
          {
            "type":"text"
            , "text":"Kernel type: Single work-item"
          }
          , {
            "type":"text"
            , "text":"Required workgroup size: (1, 1, 1)"
          }
          , {
            "type":"text"
            , "text":"Maximum workgroup size: 1"
          }
        ]
        , "debug":
        [
          [
            {
              "filename":"iamax.cl"
              , "line":19
            }
          ]
        ]
      }
    ]
  }
  , "estimatedResources":
  {
    "name":"Estimated Resource Usage"
    , "columns":
    ["Kernel Name", "ALUTs ", "FFs  ", "RAMs ", "DSPs ", "MLABs"]
    , "children":
    [
      {
        "name":"streaming_iamax"
        , "data":
        [9160, 18903, 67, 0, 82]
        , "debug":
        [
          [
            {
              "filename":"iamax.cl"
              , "line":19
            }
          ]
        ]
      }
      , {
        "name":"Global Interconnect"
        , "classes":
        ["summary-highlight", "nohover"]
        , "data":
        [2338, 4125, 0, 0, 0]
      }
      , {
        "name":"Board Interface"
        , "classes":
        ["summary-highlight", "nohover"]
        , "data":
        [13132, 20030, 112, 0, 0]
      }
      , {
        "name":"System description ROM"
        , "classes":
        ["summary-highlight", "nohover"]
        , "data":
        [2, 71, 2, 0, 0]
      }
      , {
        "name":"Total"
        , "classes":
        ["summary-highlight", "nohover"]
        , "data":
        [24632, 43129, 181, 0, 82]
        , "data_percent":
        [1.75262, 1.53436, 2.64349, 0]
      }
      , {
        "name":"Available"
        , "classes":
        ["summary-highlight", "nohover"]
        , "data":
        [1405440, 2810880, 6847, 3960, 0]
      }
    ]
  }
  , "compileWarnings":
  {
    "name":"Compile Warnings"
    , "children":
    [
    ]
  }
}
