{
  "nodes":
  [
    {
      "name":"matrixMult"
      , "id":616307384
      , "type":"kernel"
      , "children":
      [
        {
          "name":"matrixMult.B1"
          , "id":616305040
          , "type":"bb"
          , "children":
          [
            {
              "name":"Cluster 1"
              , "id":643321888
              , "type":"cluster"
            }
            , {
              "name":"Cluster 2"
              , "id":643421808
              , "type":"cluster"
            }
          ]
        }
        , {
          "name":"matrixMult.B0"
          , "id":616523024
          , "type":"bb"
          , "children":
          [
            {
              "name":"Cluster 0"
              , "id":642221392
              , "type":"cluster"
            }
          ]
        }
        , {
          "name":"matrixMult.B2"
          , "id":616523488
          , "type":"bb"
          , "children":
          [
            {
              "name":"Cluster 4"
              , "id":644630224
              , "type":"cluster"
            }
            , {
              "name":"Cluster 3"
              , "id":644536544
              , "type":"cluster"
            }
            , {
              "name":"Cluster 5"
              , "id":644664976
              , "type":"cluster"
            }
            , {
              "name":"Cluster 7"
              , "id":644956608
              , "type":"cluster"
            }
            , {
              "name":"Cluster 6"
              , "id":644955040
              , "type":"cluster"
            }
          ]
        }
      ]
    }
  ]
  , "links":
  [
  ]
}
